example.cpython-310-x86_64-linux-gnu.so
pyvsearch/__init__.py
pyvsearch/_pyvsearch.cpython-310-x86_64-linux-gnu.so
pyvsearch/_version.py
pyvsearch.libs/libgomp-e3b68c5f.so.1.0.0
pyvsearch-0.1.0.dev12.dist-info/METADATA
pyvsearch-0.1.0.dev12.dist-info/WHEEL
pyvsearch-0.1.0.dev12.dist-info/top_level.txt
pyvsearch-0.1.0.dev12.dist-info/RECORD
