Metadata-Version: 2.4
Name: pyvsearch
Version: 0.1.0.dev12
Summary: vsearch from Tencent ES
Home-page: https://cloud.tencent.com/product/es?Is=sdk-topnav
Author: vsearch
Author-email: 
License: Apache-2.0
Keywords: search nearest neighbors
Classifier: License :: OSI Approved :: Apache Software License
Classifier: Programming Language :: Python :: 3.10
Classifier: Programming Language :: Python :: 3.11
Requires-Dist: packaging
Dynamic: author
Dynamic: classifier
Dynamic: description
Dynamic: home-page
Dynamic: keywords
Dynamic: license
Dynamic: requires-dist
Dynamic: summary
